LICENSE
README.md
pyproject.toml
ct600/__init__.py
ct600/__main__.py
ct600/cli.py
ct600/computations.py
ct600/config.py
ct600/constants.py
ct600/corptax.py
ct600/exceptions.py
ct600/file_operations.py
ct600/govtalk.py
ct600/irmark.py
ct600/ixbrl.py
ct600/submission.py
ct600/test_service.py
ct600.egg-info/PKG-INFO
ct600.egg-info/SOURCES.txt
ct600.egg-info/dependency_links.txt
ct600.egg-info/entry_points.txt
ct600.egg-info/requires.txt
ct600.egg-info/top_level.txt