Metadata-Version: 2.4
Name: ct600
Version: 1.4.0
Summary: UK HMRC Corporation Tax submission
Author-email: Cybermaggedon <mark@cyberapocalypse.co.uk>
Project-URL: Homepage, https://github.com/cybermaggedon/ct600
Project-URL: Download, https://github.com/cybermaggedon/ct600/archive/refs/tags/v1.4.0.tar.gz
Classifier: Programming Language :: Python :: 3
Classifier: License :: OSI Approved :: GNU General Public License v3 or later (GPLv3+)
Classifier: Operating System :: OS Independent
Requires-Python: >=3.6
License-File: LICENSE
Requires-Dist: aiohttp
Requires-Dist: py-dmidecode
Requires-Dist: requests
Requires-Dist: ixbrl-parse
Requires-Dist: pyaml
Dynamic: license-file
